mcp_server_weather/__init__.py
mcp_server_weather/__main__.py
mcp_server_weather/weather.py
weather_garmin-0.5.0.dist-info/METADATA
weather_garmin-0.5.0.dist-info/WHEEL
weather_garmin-0.5.0.dist-info/entry_points.txt
weather_garmin-0.5.0.dist-info/RECORD
