Metadata-Version: 2.4
Name: weather-garmin
Version: 0.5.0
Summary: A MCP server project of weather query
Author-email: "J.M.Bai" <baijiaming003@gmail.com>
Requires-Python: >=3.11
Requires-Dist: httpx>=0.28.1
Requires-Dist: mcp[cli]>=1.9.2
